pydollar
