Metadata-Version: 1.0
Name: pydollar
Version: 0.1.3
Summary: pydollar provides an installable import hook to support the dollar sign ($) as valid python syntax.
Home-page: https://github.com/bjodah/pydollar
Author: Bjoern I. Dahlgren
Author-email: bjodah@gmail.com
License: BSD
Platform: UNKNOWN
